{
    "sku": "WH01",
    "variantAttributeNames": ["size_63313224a7189", "size_633132c50db9e"],
    "createdAt": "2023-10-27T01:50:22Z",
    "updatedAt": "2023-10-27T02:19:31Z",
    "productType": "configurable",
    "featured": false,
    "newArrival": false,
    "category_sort_order": null,
    "name": "Mona Pullover Hoodlie",
    "shortDescription": null,
    "description": "<div id=\"isolation-scope-9g6aw0a9x3jbp8ftbuod16944\" class=\"cms-wrapper\"><div>Whether you&#039;re after energizing activity or eye-catching apparel, the Mona Pullover is what you want. You&#039;ll stay warm and look fashionable, wherever you are.</div><br/><div> </div><br/><div> • Light green heathered hoodie. </div><br/><div> • Long-Sleeve, pullover.</div><br/><div> • Long elliptical hem for extra coverage.</div><br/><div> • Deep button placket for layering.</div><br/><div> • Double rib design.</div><br/><div> • Mid layer, mid weight.</div><br/><div> • 98% Merino Wool / 2% Spandex</div></div>",
    "productAttributes": { "size_63313224a7189": null, "size_633132c50db9e": null },
    "unitPrecisions": [{ "unit": "each", "precision": 0, "conversionRate": 1, "default": true }],
    "url": "/mona-pullover-hoodlie",
    "urls": [],
    "prices": [{ "price": "57.0000", "currencyId": "AUD", "quantity": "0", "unit": "each" }],
    "lowInventory": false,
    "upcoming": false,
    "availabilityDate": null,
    "metaTitle": null,
    "metaDescription": null,
    "metaKeywords": null
}
